coffee_sh/__init__.py
coffee_sh/main.py
coffee_sh-0.1.0.dist-info/entry_points.txt
coffee_sh-0.1.0.dist-info/WHEEL
coffee_sh-0.1.0.dist-info/METADATA
coffee_sh-0.1.0.dist-info/RECORD
