Metadata-Version: 2.1
Name: coffee-sh
Version: 0.1.0
Summary: Coffee is a command-line utility for developers who want their task list at termial
Author: Aadityansha
Requires-Python: >=3.10,<4.0
Classifier: Programming Language :: Python :: 3
Classifier: Programming Language :: Python :: 3.10
Requires-Dist: tinydb (>=4.7.0,<5.0.0)
Requires-Dist: typer[all] (>=0.6.1,<0.7.0)
